odoo/addons/purchase_manual_delivery/README.rst
odoo/addons/purchase_manual_delivery/__init__.py
odoo/addons/purchase_manual_delivery/__manifest__.py
odoo/addons/purchase_manual_delivery/i18n/purchase_manual_delivery.pot
odoo/addons/purchase_manual_delivery/i18n/sl.po
odoo/addons/purchase_manual_delivery/models/__init__.py
odoo/addons/purchase_manual_delivery/models/purchase_order.py
odoo/addons/purchase_manual_delivery/models/res_company.py
odoo/addons/purchase_manual_delivery/models/res_config.py
odoo/addons/purchase_manual_delivery/readme/CONTRIBUTORS.rst
odoo/addons/purchase_manual_delivery/readme/DESCRIPTION.rst
odoo/addons/purchase_manual_delivery/readme/USAGE.rst
odoo/addons/purchase_manual_delivery/static/description/create_incoming_shipment_button.png
odoo/addons/purchase_manual_delivery/static/description/create_incoming_shipment_wizard.png
odoo/addons/purchase_manual_delivery/static/description/icon.png
odoo/addons/purchase_manual_delivery/static/description/index.html
odoo/addons/purchase_manual_delivery/tests/__init__.py
odoo/addons/purchase_manual_delivery/tests/test_purchase_manual_delivery.py
odoo/addons/purchase_manual_delivery/views/purchase_order_views.xml
odoo/addons/purchase_manual_delivery/views/res_config_view.xml
odoo/addons/purchase_manual_delivery/wizard/__init__.py
odoo/addons/purchase_manual_delivery/wizard/create_manual_stock_picking.py
odoo/addons/purchase_manual_delivery/wizard/create_manual_stock_picking_views.xml
odoo13_addon_purchase_manual_delivery-13.0.1.0.1.dev9.dist-info/METADATA
odoo13_addon_purchase_manual_delivery-13.0.1.0.1.dev9.dist-info/WHEEL
odoo13_addon_purchase_manual_delivery-13.0.1.0.1.dev9.dist-info/top_level.txt
odoo13_addon_purchase_manual_delivery-13.0.1.0.1.dev9.dist-info/RECORD
