Metadata-Version: 2.1
Name: odoo13-addon-purchase-manual-delivery
Version: 13.0.1.0.1.dev9
Summary: Prevents pickings to be auto generated upon Purchase Order confirmation and adds the ability to manually generate them as the supplier confirms the different purchase order lines.
Home-page: https://github.com/OCA/purchase-workflow
Author: ForgeFlow S.L., Odoo Community Association (OCA)
Author-email: support@odoo-community.org
License: AGPL-3
Platform: UNKNOWN
Classifier: Programming Language :: Python
Classifier: Framework :: Odoo
Classifier: Framework :: Odoo :: 13.0
Classifier: License :: OSI Approved :: GNU Affero General Public License v3
Requires-Python: >=3.5
Requires-Dist: odoo <13.1dev,>=13.0a
